ngraph_mxnet-0.5.1.data/purelib/mxnet/LICENSE
ngraph_mxnet-0.5.1.data/purelib/mxnet/NGRAPH_LICENSE
ngraph_mxnet-0.5.1.data/purelib/mxnet/__init__.py
ngraph_mxnet-0.5.1.data/purelib/mxnet/attribute.py
ngraph_mxnet-0.5.1.data/purelib/mxnet/autograd.py
ngraph_mxnet-0.5.1.data/purelib/mxnet/base.py
ngraph_mxnet-0.5.1.data/purelib/mxnet/callback.py
ngraph_mxnet-0.5.1.data/purelib/mxnet/context.py
ngraph_mxnet-0.5.1.data/purelib/mxnet/engine.py
ngraph_mxnet-0.5.1.data/purelib/mxnet/executor.py
ngraph_mxnet-0.5.1.data/purelib/mxnet/executor_manager.py
ngraph_mxnet-0.5.1.data/purelib/mxnet/initializer.py
ngraph_mxnet-0.5.1.data/purelib/mxnet/kvstore.py
ngraph_mxnet-0.5.1.data/purelib/mxnet/kvstore_server.py
ngraph_mxnet-0.5.1.data/purelib/mxnet/libcpu_backend.so
ngraph_mxnet-0.5.1.data/purelib/mxnet/libinfo.py
ngraph_mxnet-0.5.1.data/purelib/mxnet/libinterpreter_backend.so
ngraph_mxnet-0.5.1.data/purelib/mxnet/libiomp5.so
ngraph_mxnet-0.5.1.data/purelib/mxnet/libmkldnn.so
ngraph_mxnet-0.5.1.data/purelib/mxnet/libmklml_intel.so
ngraph_mxnet-0.5.1.data/purelib/mxnet/libmxnet.so
ngraph_mxnet-0.5.1.data/purelib/mxnet/libngraph.so
ngraph_mxnet-0.5.1.data/purelib/mxnet/libngraph_test_util.so
ngraph_mxnet-0.5.1.data/purelib/mxnet/libnop_backend.so
ngraph_mxnet-0.5.1.data/purelib/mxnet/libtbb.so
ngraph_mxnet-0.5.1.data/purelib/mxnet/libtbb.so.2
ngraph_mxnet-0.5.1.data/purelib/mxnet/log.py
ngraph_mxnet-0.5.1.data/purelib/mxnet/lr_scheduler.py
ngraph_mxnet-0.5.1.data/purelib/mxnet/metric.py
ngraph_mxnet-0.5.1.data/purelib/mxnet/misc.py
ngraph_mxnet-0.5.1.data/purelib/mxnet/model.py
ngraph_mxnet-0.5.1.data/purelib/mxnet/monitor.py
ngraph_mxnet-0.5.1.data/purelib/mxnet/name.py
ngraph_mxnet-0.5.1.data/purelib/mxnet/ndarray_doc.py
ngraph_mxnet-0.5.1.data/purelib/mxnet/operator.py
ngraph_mxnet-0.5.1.data/purelib/mxnet/profiler.py
ngraph_mxnet-0.5.1.data/purelib/mxnet/random.py
ngraph_mxnet-0.5.1.data/purelib/mxnet/recordio.py
ngraph_mxnet-0.5.1.data/purelib/mxnet/registry.py
ngraph_mxnet-0.5.1.dist-info/METADATA
ngraph_mxnet-0.5.1.dist-info/WHEEL
ngraph_mxnet-0.5.1.dist-info/top_level.txt
ngraph_mxnet-0.5.1.dist-info/RECORD
