Metadata-Version: 2.1
Name: ngraph-mxnet
Version: 0.5.1
Summary: MXNet Python Package
Requires-Dist: numpy (<=1.15.2,>=1.8.2)
Requires-Dist: requests (<2.19.0,>=2.18.4)
Requires-Dist: graphviz (<0.9.0,>=0.8.1)
